{"data":[{"name":"Product Name","price":100,"description":"Product description","product":"Product type","color":"Product color","image":"https://example.com/image.jpg","createdAt":"2023-12-13T10:28:38.953Z","id":110},{"name":"Product Name","price":100,"description":"Product description","product":"Product type","color":"Product color","image":"https://example.com/image.jpg","createdAt":"2023-12-13T10:28:01.443Z","id":109},{"name":"vSDV","price":3525,"description":"sdbfsb","product":"bdsfbs","color":"bsdfbsfb","image":"bfdsbs","createdAt":"2023-12-13T10:23:44.153Z","id":106},{"name":"Product Name","price":100,"description":"Product description","product":"Product type","color":"Product color","image":"https://example.com/image.jpg","createdAt":"2023-12-13T10:22:13.070Z","id":105},{"name":"Product Name","price":100,"description":"Product description","product":"Product type","color":"Product color","image":"https://example.com/image.jpg","createdAt":"2023-12-13T10:21:39.249Z","id":104},{"name":"Product Name","price":100,"description":"Product description","product":"Product type","color":"Product color","image":"https://example.com/image.jpg","createdAt":"2023-12-13T10:21:38.629Z","id":103},{"name":"Product Name","price":100,"description":"Product description","product":"Product type","color":"Product color","image":"https://example.com/image.jpg","createdAt":"2023-12-13T10:21:36.302Z","id":49},{"name":"Product Name","price":100,"description":"Product description","product":"Product type","color":"Product color","image":"https://example.com/image.jpg","createdAt":"2023-12-13T10:09:57.893Z","id":101},{"id":82,"name":"Luxurious Cotton Hat","price":"129.00","description":"Abduco natus vero velut correptius apud laborum audentia vorax.","product":"Table","color":"red","createdAt":"2023-12-02T23:44:14.355Z","image":"https://loremflickr.com/640/480?lock=4489003615125504"},{"id":10,"name":"Modern Bronze Salad","price":"117.00","description":"Aveho vero cursus.","product":"Car","color":"magenta","createdAt":"2023-11-08T01:23:42.599Z","image":"https://loremflickr.com/640/480?lock=7621585269686272"},{"id":99,"name":"Electronic Bronze Fish","price":"580.00","description":"Necessitatibus absconditus velit spero conicio aliqua.","product":"Car","color":"fuchsia","createdAt":"2023-11-04T23:38:03.701Z","image":"https://picsum.photos/seed/8uRWu/640/480"},{"id":96,"name":"Incredible Bronze Bacon","price":"607.00","description":"Cupressus certe administratio totus suscipio spectaculum.","product":"Gloves","color":"purple","createdAt":"2023-11-01T08:12:10.609Z","image":"https://loremflickr.com/640/480?lock=2996625922326528"},{"id":95,"name":"Elegant Metal Shoes","price":"347.00","description":"Perferendis trepide sordeo temptatio nemo unus conculco.","product":"Bike","color":"orange","createdAt":"2023-10-26T14:18:57.576Z","image":"https://loremflickr.com/640/480?lock=4073792674463744"},{"id":78,"name":"Elegant Granite Chips","price":"972.00","description":"Vinum adduco peccatus apto.","product":"Tuna","color":"plum","createdAt":"2023-10-22T02:18:32.430Z","image":"https://loremflickr.com/640/480?lock=6159680248217600"},{"id":90,"name":"Gorgeous Wooden Fish","price":"404.00","description":"Cruciamentum blanditiis corrumpo callide cervus.","product":"Pizza","color":"blue","createdAt":"2023-10-22T02:10:11.543Z","image":"https://loremflickr.com/640/480?lock=8831275305533440"},{"id":62,"name":"Gorgeous Concrete Pizza","price":"123.00","description":"Suspendo qui apto reiciendis catena ante demum.","product":"Chips","color":"azure","createdAt":"2023-10-20T06:35:46.742Z","image":"https://picsum.photos/seed/nQGLt/640/480"},{"id":15,"name":"Refined Fresh Shirt","price":"781.00","description":"Cupio alo nihil sonitus crur volva.","product":"Shoes","color":"indigo","createdAt":"2023-10-08T19:19:21.031Z","image":"https://picsum.photos/seed/a9NqS/640/480"},{"id":13,"name":"Fantastic Bronze Gloves","price":"290.00","description":"Labore degenero confero addo adversus patrocinor vehemens xiphias.","product":"Pizza","color":"tan","createdAt":"2023-09-28T18:28:19.171Z","image":"https://loremflickr.com/640/480?lock=4739798814162944"},{"id":81,"name":"Refined Granite Mouse","price":"988.00","description":"Accommodo cenaculum apostolus nam sto quam aliquid.","product":"Hat","color":"turquoise","createdAt":"2023-09-28T16:39:14.504Z","image":"https://loremflickr.com/640/480?lock=4405755908194304"},{"id":87,"name":"Refined Soft Car","price":"731.00","description":"Repellat utilis necessitatibus porro canto adipisci defendo tamen decet decerno.","product":"Shirt","color":"yellow","createdAt":"2023-09-20T00:06:47.561Z","image":"https://loremflickr.com/640/480?lock=1524100254138368"},{"id":70,"name":"Ergonomic Concrete Pizza","price":"829.00","description":"Clarus ante deduco succurro caelum vis beatus.","product":"Salad","color":"red","createdAt":"2023-09-09T11:27:31.253Z","image":"https://picsum.photos/seed/nJQesCG/640/480"},{"id":71,"name":"Modern Cotton Soap","price":"961.00","description":"Allatus timor alias antiquus volva absque.","product":"Shoes","color":"sky blue","createdAt":"2023-08-23T07:25:20.837Z","image":"https://picsum.photos/seed/FThdvcrwl6/640/480"},{"id":53,"name":"Modern Granite Computer","price":"421.00","description":"Comminor denuo sonitus delinquo cumque damno vesica tabernus patior.","product":"Pants","color":"turquoise","createdAt":"2023-08-21T21:56:56.947Z","image":"https://loremflickr.com/640/480?lock=1088404198522880"},{"id":67,"name":"Elegant Bronze Shirt","price":"806.00","description":"Curtus civitas quisquam defaeco deserunt maxime ratione cuius depono.","product":"Chicken","color":"blue","createdAt":"2023-08-16T05:38:07.477Z","image":"https://loremflickr.com/640/480?lock=5630364550692864"},{"id":97,"name":"Sleek Fresh Cheese","price":"43.00","description":"Adicio terror vigor cavus cribro.","product":"Pizza","color":"orange","createdAt":"2023-08-10T07:42:22.427Z","image":"https://picsum.photos/seed/Is5XRVZKL/640/480"},{"id":21,"name":"Ergonomic Metal Computer","price":"385.00","description":"Autus vobis clamo universe.","product":"Mouse","color":"violet","createdAt":"2023-08-10T05:49:50.564Z","image":"https://loremflickr.com/640/480?lock=6048512896663552"},{"id":47,"name":"Licensed Soft Shirt","price":"379.00","description":"Laboriosam minima comptus solus.","product":"Chicken","color":"lavender","createdAt":"2023-08-08T20:48:31.866Z","image":"https://picsum.photos/seed/2TKUn/640/480"},{"id":88,"name":"Awesome Plastic Towels","price":"184.00","description":"Compono quo crustulum valde sufficio caecus arcus.","product":"Tuna","color":"tan","createdAt":"2023-08-08T16:31:06.556Z","image":"https://loremflickr.com/640/480?lock=6257991051378688"},{"id":34,"name":"Ergonomic Steel Shirt","price":"640.00","description":"Bellum angulus cursim tui coadunatio fugit.","product":"Tuna","color":"gold","createdAt":"2023-08-07T03:51:57.821Z","image":"https://loremflickr.com/640/480?lock=7137085192404992"},{"id":9,"name":"Licensed Steel Shirt","price":"658.00","description":"Suffragium umbra atque vereor infit ex.","product":"Sausages","color":"lime","createdAt":"2023-08-06T23:01:56.711Z","image":"https://picsum.photos/seed/quRyAUhkX/640/480"},{"id":91,"name":"Licensed Frozen Soap","price":"977.00","description":"Viscus brevis dolorem vapulus minus ascisco theologus.","product":"Sausages","color":"fuchsia","createdAt":"2023-08-06T03:03:54.816Z","image":"https://loremflickr.com/640/480?lock=8771675193606144"},{"id":83,"name":"Modern Bronze Chicken","price":"58.00","description":"Caveo agnosco agnosco animadverto beatus odit eligendi torrens sumo culpa.","product":"Mouse","color":"green","createdAt":"2023-08-05T07:27:12.791Z","image":"https://loremflickr.com/640/480?lock=7361281092747264"},{"id":20,"name":"Electronic Plastic Soap","price":"198.00","description":"Surculus cunctatio torqueo pax.","product":"Cheese","color":"orange","createdAt":"2023-07-18T08:52:45.208Z","image":"https://picsum.photos/seed/6MNg4o/640/480"},{"id":8,"name":"Recycled Wooden Salad","price":"759.00","description":"Velum amicitia amaritudo amet ara.","product":"Sausages","color":"plum","createdAt":"2023-07-16T01:27:42.847Z","image":"https://loremflickr.com/640/480?lock=5551130887061504"},{"id":57,"name":"Gorgeous Rubber Bacon","price":"671.00","description":"Baiulus inflammatio amoveo vere amiculum admiratio.","product":"Chair","color":"green","createdAt":"2023-07-15T23:50:53.836Z","image":"https://loremflickr.com/640/480?lock=7781313635418112"},{"id":5,"name":"Elegant Bronze Shoes","price":"740.00","description":"Ambulo vomica tempus aiunt vorax complectus tempora voluntarius.","product":"Keyboard","color":"ivory","createdAt":"2023-07-14T06:43:54.947Z","image":"https://picsum.photos/seed/9lAKCS/640/480"},{"id":46,"name":"Generic Granite Pants","price":"887.00","description":"Absque solum voro villa consuasor.","product":"Gloves","color":"grey","createdAt":"2023-07-14T06:26:47.534Z","image":"https://picsum.photos/seed/z6Jl9zDSx/640/480"},{"id":92,"name":"Refined Plastic Pizza","price":"732.00","description":"Quibusdam ulterius copiose atrox tenus dedico artificiose comedo.","product":"Table","color":"grey","createdAt":"2023-07-09T17:39:06.066Z","image":"https://loremflickr.com/640/480?lock=1463421740515328"},{"id":64,"name":"Sleek Metal Soap","price":"899.00","description":"Trado pecus cohibeo aperio atque suasoria.","product":"Hat","color":"purple","createdAt":"2023-07-08T20:57:44.289Z","image":"https://picsum.photos/seed/rb8d8JkGB/640/480"},{"id":69,"name":"Licensed Cotton Towels","price":"215.00","description":"Impedit celebrer suus neque complectus terror adhaero.","product":"Shirt","color":"mint green","createdAt":"2023-07-05T01:34:31.135Z","image":"https://loremflickr.com/640/480?lock=4389134160363520"},{"id":76,"name":"Licensed Soft Hat","price":"662.00","description":"Alias strues libero cenaculum vulticulus.","product":"Chair","color":"violet","createdAt":"2023-07-01T14:31:04.092Z","image":"https://loremflickr.com/640/480?lock=4175352146427904"},{"id":24,"name":"Incredible Granite Keyboard","price":"68.00","description":"Vitium spectaculum modi perspiciatis demitto decet aegrotatio valde id arguo.","product":"Towels","color":"sky blue","createdAt":"2023-06-28T11:54:40.661Z","image":"https://loremflickr.com/640/480?lock=7668643139682304"},{"id":11,"name":"Elegant Plastic Pizza","price":"238.00","description":"Audacia suus civitas voluptatem virga cubicularis caveo doloremque adsidue alter.","product":"Sausages","color":"azure","createdAt":"2023-06-28T04:41:17.707Z","image":"https://picsum.photos/seed/hMRS9/640/480"},{"id":25,"name":"Bespoke Fresh Table","price":"632.00","description":"Tametsi dolor vulticulus facilis inventore ancilla adipisci tergum absorbeo ademptio.","product":"Computer","color":"black","createdAt":"2023-06-24T18:13:51.119Z","image":"https://picsum.photos/seed/fJeSYs4d6N/640/480"},{"id":74,"name":"Unbranded Granite Fish","price":"30.00","description":"Quam demum perspiciatis tener surgo aegrotatio armarium.","product":"Chair","color":"mint green","createdAt":"2023-06-23T12:10:21.496Z","image":"https://loremflickr.com/640/480?lock=8914364524396544"},{"id":29,"name":"Oriental Plastic Gloves","price":"517.00","description":"Texo aequitas vitiosus.","product":"Towels","color":"orchid","createdAt":"2023-06-22T12:08:08.521Z","image":"https://loremflickr.com/640/480?lock=6797903391621120"},{"id":58,"name":"Refined Fresh Keyboard","price":"358.00","description":"Cernuus expedita utilis degenero summa vis sollers adimpleo calcar thesaurus.","product":"Chair","color":"purple","createdAt":"2023-06-20T11:08:29.405Z","image":"https://loremflickr.com/640/480?lock=5129102881193984"},{"id":94,"name":"Handmade Plastic Shirt","price":"858.00","description":"Sophismata accusator tabgo adhuc comprehendo arguo.","product":"Tuna","color":"orchid","createdAt":"2023-06-19T21:27:24.154Z","image":"https://picsum.photos/seed/bY4cf/640/480"},{"id":27,"name":"Electronic Bronze Chips","price":"505.00","description":"Vulgo cariosus utrimque defendo universe titulus quis vivo veritatis.","product":"Fish","color":"black","createdAt":"2023-06-12T10:27:11.431Z","image":"https://picsum.photos/seed/pZz28rirt4/640/480"},{"id":28,"name":"Ergonomic Rubber Mouse","price":"323.00","description":"Agnosco sulum attonbitus tempore tabesco adeo cubicularis adeptio audentia arbustum.","product":"Cheese","color":"green","createdAt":"2023-06-11T07:29:58.822Z","image":"https://picsum.photos/seed/yiJnios/640/480"},{"id":38,"name":"Electronic Steel Chair","price":"243.00","description":"Cum claro bis verecundia vereor spiculum tergo pax nesciunt condico.","product":"Gloves","color":"turquoise","createdAt":"2023-06-09T21:32:14.019Z","image":"https://loremflickr.com/640/480?lock=6367930266681344"},{"id":16,"name":"Fantastic Soft Chair","price":"730.00","description":"Cito esse vulpes ipsum aestus voveo ulterius.","product":"Tuna","color":"lime","createdAt":"2023-06-09T14:49:34.234Z","image":"https://loremflickr.com/640/480?lock=6354811068874752"},{"id":55,"name":"Gorgeous Granite Fish","price":"123.00","description":"Damnatio utpote decumbo stipes tempore urbs.","product":"Pants","color":"yellow","createdAt":"2023-06-07T14:59:37.786Z","image":"https://loremflickr.com/640/480?lock=6527471442722816"},{"id":86,"name":"Awesome Metal Pants","price":"80.00","description":"Deserunt cito repellendus ultio quasi addo atrox aspernatur.","product":"Tuna","color":"sky blue","createdAt":"2023-06-07T07:45:03.353Z","image":"https://picsum.photos/seed/4Fbbb/640/480"},{"id":18,"name":"Practical Bronze Bacon","price":"813.00","description":"Sustineo beneficium studio bibo aiunt.","product":"Chair","color":"yellow","createdAt":"2023-05-23T08:13:01.497Z","image":"https://picsum.photos/seed/jLna2F54/640/480"},{"id":40,"name":"Gorgeous Fresh Pizza","price":"746.00","description":"Laboriosam cuius varietas victus.","product":"Cheese","color":"violet","createdAt":"2023-05-18T07:46:13.335Z","image":"https://picsum.photos/seed/YdZZli/640/480"},{"id":61,"name":"Small Fresh Pizza","price":"588.00","description":"Asperiores iste alveus.","product":"Chicken","color":"mint green","createdAt":"2023-05-15T13:47:37.875Z","image":"https://loremflickr.com/640/480?lock=1645932833669120"},{"id":77,"name":"Recycled Cotton Fish","price":"935.00","description":"Maiores summa nesciunt asperiores victus turbo demitto verecundia.","product":"Bacon","color":"black","createdAt":"2023-05-10T14:41:28.173Z","image":"https://loremflickr.com/640/480?lock=7440847817670656"},{"id":22,"name":"Unbranded Frozen Salad","price":"365.00","description":"Ultio universe cupressus traho.","product":"Mouse","color":"black","createdAt":"2023-05-08T13:10:56.596Z","image":"https://picsum.photos/seed/AyELsTOd7K/640/480"},{"id":93,"name":"Rustic Cotton Pants","price":"743.00","description":"Tremo volva sublime.","product":"Chips","color":"red","createdAt":"2023-05-08T09:08:51.594Z","image":"https://loremflickr.com/640/480?lock=5663482028490752"},{"id":68,"name":"Handmade Fresh Hat","price":"365.00","description":"Terra conduco aestivus patria utroque quisquam mollitia appello.","product":"Ball","color":"orchid","createdAt":"2023-05-08T03:38:01.083Z","image":"https://loremflickr.com/640/480?lock=8455507817791488"},{"id":50,"name":"Fantastic Rubber Shoes","price":"942.00","description":"Vomer rerum exercitationem amor surculus denique vulticulus vomito suffragium consuasor.","product":"Keyboard","color":"silver","createdAt":"2023-05-04T13:12:17.492Z","image":"https://picsum.photos/seed/UPilO3tg/640/480"},{"id":37,"name":"Electronic Soft Bike","price":"765.00","description":"Non spectaculum statim chirographum harum canis deleniti.","product":"Table","color":"gold","createdAt":"2023-04-30T19:25:28.304Z","image":"https://picsum.photos/seed/ViJ9pFflaE/640/480"},{"id":85,"name":"Electronic Steel Bike","price":"100.00","description":"Vinum distinctio maiores bestia.","product":"Salad","color":"salmon","createdAt":"2023-04-22T03:17:25.531Z","image":"https://picsum.photos/seed/C5HBea6/640/480"},{"id":89,"name":"Elegant Wooden Bacon","price":"391.00","description":"Vesper adficio damno alveus vitae virga.","product":"Computer","color":"yellow","createdAt":"2023-04-19T23:40:19.590Z","image":"https://picsum.photos/seed/iV0unQc/640/480"},{"id":33,"name":"Fantastic Frozen Soap","price":"992.00","description":"Adsidue laborum statim termes arguo beatus tendo crinis audio.","product":"Keyboard","color":"orange","createdAt":"2023-04-19T08:07:13.373Z","image":"https://picsum.photos/seed/ayau1cw/640/480"},{"id":2,"name":"Electronic Metal Towels","price":"789.00","description":"Tutis aer uter curso optio velut condico casus succedo.","product":"Chips","color":"black","createdAt":"2023-04-19T00:12:53.072Z","image":"https://loremflickr.com/640/480?lock=8380168466857984"},{"id":36,"name":"Gorgeous Fresh Keyboard","price":"162.00","description":"Ante statua audeo quisquam doloremque coerceo in vitae.","product":"Computer","color":"gold","createdAt":"2023-04-18T02:06:24.902Z","image":"https://picsum.photos/seed/7dhp2BRe/640/480"},{"id":80,"name":"Sleek Bronze Cheese","price":"761.00","description":"Summopere auctor vitium sumptus congregatio aestivus bestia impedit advenio vesper.","product":"Shirt","color":"maroon","createdAt":"2023-04-13T15:44:06.313Z","image":"https://picsum.photos/seed/gcu8P/640/480"},{"id":66,"name":"Intelligent Metal Gloves","price":"932.00","description":"Thesaurus magni tam certus ter coniecto umbra.","product":"Towels","color":"orange","createdAt":"2023-04-12T09:46:16.456Z","image":"https://loremflickr.com/640/480?lock=3544332468486144"},{"id":30,"name":"Fantastic Metal Ball","price":"894.00","description":"Velum tolero carbo.","product":"Fish","color":"red","createdAt":"2023-04-11T08:33:58.656Z","image":"https://picsum.photos/seed/FVB5dbveC/640/480"},{"id":51,"name":"Fantastic Cotton Bike","price":"259.00","description":"Patruus contigo validus tero ambitus abstergo dolores utroque.","product":"Fish","color":"grey","createdAt":"2023-04-09T13:47:23.000Z","image":"https://loremflickr.com/640/480?lock=2907282312527872"},{"id":26,"name":"Electronic Frozen Chicken","price":"885.00","description":"Ver acervus eum magnam ars considero amo curis repellendus paens.","product":"Bacon","color":"orchid","createdAt":"2023-04-06T18:30:16.884Z","image":"https://loremflickr.com/640/480?lock=6115645538172928"},{"id":14,"name":"Refined Concrete Car","price":"533.00","description":"Stabilis pauper neque surgo assentator aduro ars.","product":"Table","color":"teal","createdAt":"2023-04-02T22:19:49.117Z","image":"https://picsum.photos/seed/JBrNtMs/640/480"},{"id":52,"name":"Handcrafted Rubber Bike","price":"926.00","description":"Carus constans vesco veritatis excepturi celo.","product":"Chair","color":"gold","createdAt":"2023-03-28T12:13:13.371Z","image":"https://loremflickr.com/640/480?lock=816448167477248"},{"id":7,"name":"Recycled Metal Shoes","price":"207.00","description":"Cibus excepturi degusto aperte vulnero tremo temporibus claudeo.","product":"Computer","color":"green","createdAt":"2023-03-23T01:59:50.581Z","image":"https://picsum.photos/seed/RYXb6eQvfT/640/480"},{"id":12,"name":"Small Rubber Soap","price":"286.00","description":"Vetus apparatus ipsum.","product":"Towels","color":"mint green","createdAt":"2023-03-21T23:06:33.131Z","image":"https://picsum.photos/seed/3d8ZcJ/640/480"},{"id":63,"name":"Bespoke Frozen Mouse","price":"197.00","description":"Auxilium culpo denego volubilis carus ipsa cavus amita tollo.","product":"Pizza","color":"plum","createdAt":"2023-03-17T01:36:55.986Z","image":"https://loremflickr.com/640/480?lock=264573982605312"},{"id":75,"name":"Handmade Granite Car","price":"48.00","description":"Optio ascit aestas trucido alioqui fuga villa eos admitto templum.","product":"Soap","color":"tan","createdAt":"2023-03-11T10:16:09.558Z","image":"https://picsum.photos/seed/dzQxu/640/480"},{"id":4,"name":"Unbranded Cotton Chicken","price":"519.00","description":"Toties advoco similique concido.","product":"Computer","color":"orange","createdAt":"2023-03-09T22:09:38.316Z","image":"https://picsum.photos/seed/hHVHips/640/480"},{"id":54,"name":"Bespoke Plastic Hat","price":"557.00","description":"Clementia alias sum absum.","product":"Pants","color":"lavender","createdAt":"2023-03-09T19:17:11.978Z","image":"https://picsum.photos/seed/f8E7xDy/640/480"},{"id":32,"name":"Modern Concrete Shoes","price":"312.00","description":"Labore cotidie solvo viscus thorax terminatio delicate.","product":"Gloves","color":"gold","createdAt":"2023-03-08T17:01:28.962Z","image":"https://picsum.photos/seed/lGraeAjlSp/640/480"},{"id":44,"name":"Refined Metal Bike","price":"728.00","description":"Comes aliquid copiose.","product":"Gloves","color":"azure","createdAt":"2023-03-02T16:26:50.502Z","image":"https://loremflickr.com/640/480?lock=479749711331328"},{"id":19,"name":"Practical Fresh Shoes","price":"192.00","description":"Reprehenderit sunt abundans nobis curso maxime.","product":"Bike","color":"teal","createdAt":"2023-03-01T18:00:49.468Z","image":"https://loremflickr.com/640/480?lock=376336384262144"},{"id":60,"name":"Sleek Frozen Chair","price":"5.00","description":"Audacia cribro venustas sapiente damnatio tepesco sono.","product":"Fish","color":"teal","createdAt":"2023-03-01T06:19:30.779Z","image":"https://loremflickr.com/640/480?lock=6540044686852096"},{"id":79,"name":"Gorgeous Metal Fish","price":"699.00","description":"Quibusdam cupiditas fuga casso abundans sophismata.","product":"Bike","color":"red","createdAt":"2023-02-26T04:29:16.005Z","image":"https://loremflickr.com/640/480?lock=962726073466880"},{"id":84,"name":"Refined Metal Cheese","price":"104.00","description":"Sum surgo ceno.","product":"Tuna","color":"silver","createdAt":"2023-02-24T23:12:23.340Z","image":"https://picsum.photos/seed/sTlLdNGpap/640/480"},{"id":42,"name":"Incredible Plastic Shoes","price":"552.00","description":"Accusantium balbus comptus eius accendo.","product":"Chicken","color":"silver","createdAt":"2023-02-14T05:38:41.782Z","image":"https://loremflickr.com/640/480?lock=6811709454942208"},{"id":72,"name":"Intelligent Cotton Chicken","price":"766.00","description":"Tero acer stillicidium veritas combibo cognomen.","product":"Bike","color":"black","createdAt":"2023-02-10T17:09:47.174Z","image":"https://loremflickr.com/640/480?lock=7122922107830272"},{"id":43,"name":"Small Soft Gloves","price":"501.00","description":"Ceno spoliatio crudelis adfectus cilicium.","product":"Mouse","color":"green","createdAt":"2023-02-09T23:36:43.080Z","image":"https://loremflickr.com/640/480?lock=1269624989548544"},{"id":35,"name":"Bespoke Steel Hat","price":"197.00","description":"Validus decimus accusantium optio volo aliqua bellicus valens tempore tepesco.","product":"Keyboard","color":"sky blue","createdAt":"2023-01-31T07:51:58.291Z","image":"https://picsum.photos/seed/tnfueuNv/640/480"},{"id":17,"name":"Gorgeous Steel Chicken","price":"219.00","description":"Tondeo demens acer apto doloremque ventosus.","product":"Sausages","color":"orange","createdAt":"2023-01-30T21:01:05.435Z","image":"https://loremflickr.com/640/480?lock=6812232943927296"},{"id":48,"name":"Practical Metal Soap","price":"771.00","description":"Viduo depopulo triduana aedificium tempora.","product":"Fish","color":"pink","createdAt":"2023-01-18T23:08:59.041Z","image":"https://picsum.photos/seed/xCrsCsST/640/480"},{"id":73,"name":"Recycled Wooden Hat","price":"721.00","description":"Sordeo subito caelestis vulgaris thymbra abutor combibo ducimus.","product":"Tuna","color":"red","createdAt":"2023-01-12T16:31:51.283Z","image":"https://loremflickr.com/640/480?lock=6284030840406016"},{"id":65,"name":"Bespoke Plastic Chicken","price":"932.00","description":"Desino ver ubi timor admoneo amor.","product":"Car","color":"teal","createdAt":"2023-01-09T01:25:41.625Z","image":"https://loremflickr.com/640/480?lock=1512422244352000"},{"id":41,"name":"Small Plastic Computer","price":"932.00","description":"Thymum tactus vereor eveniet adamo blanditiis doloremque ipsam.","product":"Bacon","color":"cyan","createdAt":"2023-01-08T02:32:35.231Z","image":"https://picsum.photos/seed/1xU8P/640/480"},{"id":98,"name":"Electronic Frozen Shoes","price":"849.00","description":"Undique catena tempore sordeo cruentus vicinus.","product":"Table","color":"white","createdAt":"2022-12-30T11:32:41.780Z","image":"https://loremflickr.com/640/480?lock=5011011104931840"},{"id":6,"name":"Electronic Rubber Salad","price":"585.00","description":"Eaque vesper defungo clementia denego vero currus.","product":"Mouse","color":"pink","createdAt":"2022-12-30T08:51:00.364Z","image":"https://loremflickr.com/640/480?lock=4764406718136320"},{"id":39,"name":"Ergonomic Rubber Shirt","price":"682.00","description":"Animi at atqui cribro ante minima ducimus.","product":"Cheese","color":"magenta","createdAt":"2022-12-30T07:36:13.848Z","image":"https://loremflickr.com/640/480?lock=5785790365827072"},{"id":31,"name":"Ergonomic Frozen Shoes","price":"55.00","description":"Catena assentator spoliatio nisi omnis defendo tenetur cilicium cubicularis.","product":"Mouse","color":"purple","createdAt":"2022-12-22T20:54:47.679Z","image":"https://picsum.photos/seed/3nGKx1ou1o/640/480"},{"id":100,"name":"Practical Frozen Towels","price":"412.00","description":"Dedecor vir animadverto accommodo crapula alias allatus capio.","product":"Hat","color":"indigo","createdAt":"2022-12-20T15:35:37.702Z","image":"https://loremflickr.com/640/480?lock=6007871946883072"},{"id":56,"name":"Ergonomic Frozen Chicken","price":"105.00","description":"Taceo debilito succurro tripudio cruentus.","product":"Bacon","color":"orchid","createdAt":"2022-12-14T11:25:17.253Z","image":"https://loremflickr.com/640/480?lock=4552114359500800"}]}